Metadata-Version: 1.1
Name: bdoccore
Version: 0.0.0
Summary: Black Desert core library for private modules
Home-page: https://github.com/RealImperialGames/BDOC-core.git
Author: Netzulo Open Source
Author-email: netzuleando@gmail.com
License:                     GNU AFFERO GENERAL PUBLIC LICENSE
